grv/__init__.py
grv/cli.py
grv/config.py
grv/constants.py
grv/git.py
grv/menu.py
grv/status.py
grv-0.0.6.dist-info/METADATA
grv-0.0.6.dist-info/WHEEL
grv-0.0.6.dist-info/entry_points.txt
grv-0.0.6.dist-info/licenses/LICENSE
grv-0.0.6.dist-info/RECORD
