Metadata-Version: 2.4
Name: grv
Version: 0.0.6
Summary: Git workspace manager using worktrees
License-Expression: MIT
License-File: LICENSE
Requires-Python: >=3.12
Requires-Dist: click>=8.1.0
Requires-Dist: simple-term-menu>=1.6.0
